jupyter_space/__init__.py
jupyter_space/_version.py
jupyter_space/handlers.py
jupyter_space/tests/__init__.py
jupyter_space/tests/test_handlers.py
jupyter_space-0.0.2.data/data/etc/jupyter/jupyter_notebook_config.d/jupyter_space.json
jupyter_space-0.0.2.data/data/etc/jupyter/jupyter_server_config.d/jupyter_space.json
jupyter_space-0.0.2.data/data/share/jupyter/labextensions/@datalayer/jupyter-space/build_log.json
jupyter_space-0.0.2.data/data/share/jupyter/labextensions/@datalayer/jupyter-space/package.json
jupyter_space-0.0.2.data/data/share/jupyter/labextensions/@datalayer/jupyter-space/schemas/@datalayer/jupyter-earth/package.json.orig
jupyter_space-0.0.2.data/data/share/jupyter/labextensions/@datalayer/jupyter-space/schemas/@datalayer/jupyter-earth/plugin.json
jupyter_space-0.0.2.data/data/share/jupyter/labextensions/@datalayer/jupyter-space/static/design_icons_lib_index_js.e638e26156b263162373.js
jupyter_space-0.0.2.data/data/share/jupyter/labextensions/@datalayer/jupyter-space/static/design_icons_lib_index_js.e638e26156b263162373.js.map
jupyter_space-0.0.2.data/data/share/jupyter/labextensions/@datalayer/jupyter-space/static/lib_index_js.a0eb343f6207bcc2ee80.js
jupyter_space-0.0.2.data/data/share/jupyter/labextensions/@datalayer/jupyter-space/static/lib_index_js.a0eb343f6207bcc2ee80.js.map
jupyter_space-0.0.2.data/data/share/jupyter/labextensions/@datalayer/jupyter-space/static/remoteEntry.7f68430b1c4d6a024f4e.js
jupyter_space-0.0.2.data/data/share/jupyter/labextensions/@datalayer/jupyter-space/static/remoteEntry.7f68430b1c4d6a024f4e.js.map
jupyter_space-0.0.2.data/data/share/jupyter/labextensions/@datalayer/jupyter-space/static/style.js
jupyter_space-0.0.2.data/data/share/jupyter/labextensions/@datalayer/jupyter-space/static/style_index_js.dad7be19c2afbf1f786f.js
jupyter_space-0.0.2.data/data/share/jupyter/labextensions/@datalayer/jupyter-space/static/style_index_js.dad7be19c2afbf1f786f.js.map
jupyter_space-0.0.2.dist-info/METADATA
jupyter_space-0.0.2.dist-info/WHEEL
jupyter_space-0.0.2.dist-info/licenses/LICENSE
jupyter_space-0.0.2.dist-info/RECORD
